<document>
 <table id="Table 1">
  <caption text="

   Percentage of the misclassified trade flows at the 6-digit level. Measurement error (ME) is defined in
   as the percentage of the total value of trade flows in the extraction equipment that are falsely classified as sanctioned when using data disaggregated by 6-digit HS codes.
  
">
  </caption>
  <row row="0">
   <cell col-end="0" col-start="0" row-end="0" row-start="0" text="Year">
    <evidence statement_id="0" type="irrelevant" version="0">
    </evidence>
    <evidence statement_id="1" type="irrelevant" version="0">
    </evidence>
    <evidence statement_id="2" type="irrelevant" version="0">
    </evidence>
    <evidence statement_id="3" type="relevant" version="0">
    </evidence>
    <evidence statement_id="4" type="relevant" version="0">
    </evidence>
    <evidence statement_id="5" type="relevant" version="0">
    </evidence>
    <evidence statement_id="6" type="irrelevant" version="0">
    </evidence>
    <evidence statement_id="7" type="irrelevant" version="0">
    </evidence>
    <evidence statement_id="8" type="irrelevant" version="0">
    </evidence>
    <evidence statement_id="9" type="irrelevant" version="0">
    </evidence>
   </cell>
   <cell col-end="1" col-start="1" row-end="0" row-start="0" text="ME">
    <evidence statement_id="0" type="relevant" version="0">
    </evidence>
    <evidence statement_id="1" type="irrelevant" version="0">
    </evidence>
    <evidence statement_id="2" type="irrelevant" version="0">
    </evidence>
    <evidence statement_id="3" type="relevant" version="0">
    </evidence>
    <evidence statement_id="4" type="irrelevant" version="0">
    </evidence>
    <evidence statement_id="5" type="irrelevant" version="0">
    </evidence>
    <evidence statement_id="6" type="relevant" version="0">
    </evidence>
    <evidence statement_id="7" type="relevant" version="0">
    </evidence>
    <evidence statement_id="8" type="relevant" version="0">
    </evidence>
    <evidence statement_id="9" type="relevant" version="0">
    </evidence>
   </cell>
   <cell col-end="2" col-start="2" row-end="0" row-start="0" text="Year">
    <evidence statement_id="0" type="irrelevant" version="0">
    </evidence>
    <evidence statement_id="1" type="relevant" version="0">
    </evidence>
    <evidence statement_id="2" type="relevant" version="0">
    </evidence>
    <evidence statement_id="3" type="relevant" version="0">
    </evidence>
    <evidence statement_id="4" type="relevant" version="0">
    </evidence>
    <evidence statement_id="5" type="relevant" version="0">
    </evidence>
    <evidence statement_id="6" type="irrelevant" version="0">
    </evidence>
    <evidence statement_id="7" type="relevant" version="0">
    </evidence>
    <evidence statement_id="8" type="irrelevant" version="0">
    </evidence>
    <evidence statement_id="9" type="relevant" version="0">
    </evidence>
   </cell>
   <cell col-end="3" col-start="3" row-end="0" row-start="0" text="ME">
    <evidence statement_id="0" type="relevant" version="0">
    </evidence>
    <evidence statement_id="1" type="relevant" version="0">
    </evidence>
    <evidence statement_id="2" type="relevant" version="0">
    </evidence>
    <evidence statement_id="3" type="relevant" version="0">
    </evidence>
    <evidence statement_id="4" type="irrelevant" version="0">
    </evidence>
    <evidence statement_id="5" type="irrelevant" version="0">
    </evidence>
    <evidence statement_id="6" type="relevant" version="0">
    </evidence>
    <evidence statement_id="7" type="relevant" version="0">
    </evidence>
    <evidence statement_id="8" type="relevant" version="0">
    </evidence>
    <evidence statement_id="9" type="relevant" version="0">
    </evidence>
   </cell>
  </row>
  <row row="1">
   <cell col-end="0" col-start="0" row-end="1" row-start="1" text="2010">
    <evidence statement_id="0" type="irrelevant" version="0">
    </evidence>
    <evidence statement_id="1" type="irrelevant" version="0">
    </evidence>
    <evidence statement_id="2" type="irrelevant" version="0">
    </evidence>
    <evidence statement_id="3" type="relevant" version="0">
    </evidence>
    <evidence statement_id="4" type="relevant" version="0">
    </evidence>
    <evidence statement_id="5" type="relevant" version="0">
    </evidence>
    <evidence statement_id="6" type="irrelevant" version="0">
    </evidence>
    <evidence statement_id="7" type="irrelevant" version="0">
    </evidence>
    <evidence statement_id="8" type="irrelevant" version="0">
    </evidence>
    <evidence statement_id="9" type="irrelevant" version="0">
    </evidence>
   </cell>
   <cell col-end="1" col-start="1" row-end="1" row-start="1" text="6.78%">
    <evidence statement_id="0" type="relevant" version="0">
    </evidence>
    <evidence statement_id="1" type="irrelevant" version="0">
    </evidence>
    <evidence statement_id="2" type="irrelevant" version="0">
    </evidence>
    <evidence statement_id="3" type="relevant" version="0">
    </evidence>
    <evidence statement_id="4" type="irrelevant" version="0">
    </evidence>
    <evidence statement_id="5" type="irrelevant" version="0">
    </evidence>
    <evidence statement_id="6" type="relevant" version="0">
    </evidence>
    <evidence statement_id="7" type="relevant" version="0">
    </evidence>
    <evidence statement_id="8" type="relevant" version="0">
    </evidence>
    <evidence statement_id="9" type="relevant" version="0">
    </evidence>
   </cell>
   <cell col-end="2" col-start="2" row-end="1" row-start="1" text="2015">
    <evidence statement_id="0" type="irrelevant" version="0">
    </evidence>
    <evidence statement_id="1" type="irrelevant" version="0">
    </evidence>
    <evidence statement_id="2" type="irrelevant" version="0">
    </evidence>
    <evidence statement_id="3" type="relevant" version="0">
    </evidence>
    <evidence statement_id="4" type="relevant" version="0">
    </evidence>
    <evidence statement_id="5" type="relevant" version="0">
    </evidence>
    <evidence statement_id="6" type="irrelevant" version="0">
    </evidence>
    <evidence statement_id="7" type="irrelevant" version="0">
    </evidence>
    <evidence statement_id="8" type="irrelevant" version="0">
    </evidence>
    <evidence statement_id="9" type="irrelevant" version="0">
    </evidence>
   </cell>
   <cell col-end="3" col-start="3" row-end="1" row-start="1" text="1.04%">
    <evidence statement_id="0" type="relevant" version="0">
    </evidence>
    <evidence statement_id="1" type="irrelevant" version="0">
    </evidence>
    <evidence statement_id="2" type="irrelevant" version="0">
    </evidence>
    <evidence statement_id="3" type="relevant" version="0">
    </evidence>
    <evidence statement_id="4" type="irrelevant" version="0">
    </evidence>
    <evidence statement_id="5" type="irrelevant" version="0">
    </evidence>
    <evidence statement_id="6" type="relevant" version="0">
    </evidence>
    <evidence statement_id="7" type="relevant" version="0">
    </evidence>
    <evidence statement_id="8" type="relevant" version="0">
    </evidence>
    <evidence statement_id="9" type="relevant" version="0">
    </evidence>
   </cell>
  </row>
  <row row="2">
   <cell col-end="0" col-start="0" row-end="2" row-start="2" text="2011">
    <evidence statement_id="0" type="irrelevant" version="0">
    </evidence>
    <evidence statement_id="1" type="irrelevant" version="0">
    </evidence>
    <evidence statement_id="2" type="irrelevant" version="0">
    </evidence>
    <evidence statement_id="3" type="irrelevant" version="0">
    </evidence>
    <evidence statement_id="4" type="relevant" version="0">
    </evidence>
    <evidence statement_id="5" type="relevant" version="0">
    </evidence>
    <evidence statement_id="6" type="irrelevant" version="0">
    </evidence>
    <evidence statement_id="7" type="irrelevant" version="0">
    </evidence>
    <evidence statement_id="8" type="irrelevant" version="0">
    </evidence>
    <evidence statement_id="9" type="irrelevant" version="0">
    </evidence>
   </cell>
   <cell col-end="1" col-start="1" row-end="2" row-start="2" text="1.23%">
    <evidence statement_id="0" type="relevant" version="0">
    </evidence>
    <evidence statement_id="1" type="irrelevant" version="0">
    </evidence>
    <evidence statement_id="2" type="irrelevant" version="0">
    </evidence>
    <evidence statement_id="3" type="irrelevant" version="0">
    </evidence>
    <evidence statement_id="4" type="irrelevant" version="0">
    </evidence>
    <evidence statement_id="5" type="irrelevant" version="0">
    </evidence>
    <evidence statement_id="6" type="relevant" version="0">
    </evidence>
    <evidence statement_id="7" type="relevant" version="0">
    </evidence>
    <evidence statement_id="8" type="relevant" version="0">
    </evidence>
    <evidence statement_id="9" type="relevant" version="0">
    </evidence>
   </cell>
   <cell col-end="2" col-start="2" row-end="2" row-start="2" text="2016">
    <evidence statement_id="0" type="irrelevant" version="0">
    </evidence>
    <evidence statement_id="1" type="irrelevant" version="0">
    </evidence>
    <evidence statement_id="2" type="relevant" version="0">
    </evidence>
    <evidence statement_id="3" type="irrelevant" version="0">
    </evidence>
    <evidence statement_id="4" type="relevant" version="0">
    </evidence>
    <evidence statement_id="5" type="relevant" version="0">
    </evidence>
    <evidence statement_id="6" type="irrelevant" version="0">
    </evidence>
    <evidence statement_id="7" type="relevant" version="0">
    </evidence>
    <evidence statement_id="8" type="irrelevant" version="0">
    </evidence>
    <evidence statement_id="9" type="irrelevant" version="0">
    </evidence>
   </cell>
   <cell col-end="3" col-start="3" row-end="2" row-start="2" text="9.50%">
    <evidence statement_id="0" type="relevant" version="0">
    </evidence>
    <evidence statement_id="1" type="irrelevant" version="0">
    </evidence>
    <evidence statement_id="2" type="relevant" version="0">
    </evidence>
    <evidence statement_id="3" type="irrelevant" version="0">
    </evidence>
    <evidence statement_id="4" type="irrelevant" version="0">
    </evidence>
    <evidence statement_id="5" type="irrelevant" version="0">
    </evidence>
    <evidence statement_id="6" type="relevant" version="0">
    </evidence>
    <evidence statement_id="7" type="relevant" version="0">
    </evidence>
    <evidence statement_id="8" type="relevant" version="0">
    </evidence>
    <evidence statement_id="9" type="relevant" version="0">
    </evidence>
   </cell>
  </row>
  <row row="3">
   <cell col-end="0" col-start="0" row-end="3" row-start="3" text="2012">
    <evidence statement_id="0" type="irrelevant" version="0">
    </evidence>
    <evidence statement_id="1" type="irrelevant" version="0">
    </evidence>
    <evidence statement_id="2" type="irrelevant" version="0">
    </evidence>
    <evidence statement_id="3" type="irrelevant" version="0">
    </evidence>
    <evidence statement_id="4" type="relevant" version="0">
    </evidence>
    <evidence statement_id="5" type="relevant" version="0">
    </evidence>
    <evidence statement_id="6" type="irrelevant" version="0">
    </evidence>
    <evidence statement_id="7" type="irrelevant" version="0">
    </evidence>
    <evidence statement_id="8" type="irrelevant" version="0">
    </evidence>
    <evidence statement_id="9" type="irrelevant" version="0">
    </evidence>
   </cell>
   <cell col-end="1" col-start="1" row-end="3" row-start="3" text="1.87%">
    <evidence statement_id="0" type="relevant" version="0">
    </evidence>
    <evidence statement_id="1" type="irrelevant" version="0">
    </evidence>
    <evidence statement_id="2" type="irrelevant" version="0">
    </evidence>
    <evidence statement_id="3" type="irrelevant" version="0">
    </evidence>
    <evidence statement_id="4" type="irrelevant" version="0">
    </evidence>
    <evidence statement_id="5" type="irrelevant" version="0">
    </evidence>
    <evidence statement_id="6" type="relevant" version="0">
    </evidence>
    <evidence statement_id="7" type="relevant" version="0">
    </evidence>
    <evidence statement_id="8" type="relevant" version="0">
    </evidence>
    <evidence statement_id="9" type="relevant" version="0">
    </evidence>
   </cell>
   <cell col-end="2" col-start="2" row-end="3" row-start="3" text="2017">
    <evidence statement_id="0" type="irrelevant" version="0">
    </evidence>
    <evidence statement_id="1" type="irrelevant" version="0">
    </evidence>
    <evidence statement_id="2" type="irrelevant" version="0">
    </evidence>
    <evidence statement_id="3" type="irrelevant" version="0">
    </evidence>
    <evidence statement_id="4" type="relevant" version="0">
    </evidence>
    <evidence statement_id="5" type="relevant" version="0">
    </evidence>
    <evidence statement_id="6" type="irrelevant" version="0">
    </evidence>
    <evidence statement_id="7" type="irrelevant" version="0">
    </evidence>
    <evidence statement_id="8" type="irrelevant" version="0">
    </evidence>
    <evidence statement_id="9" type="irrelevant" version="0">
    </evidence>
   </cell>
   <cell col-end="3" col-start="3" row-end="3" row-start="3" text="0.94%">
    <evidence statement_id="0" type="relevant" version="0">
    </evidence>
    <evidence statement_id="1" type="irrelevant" version="0">
    </evidence>
    <evidence statement_id="2" type="irrelevant" version="0">
    </evidence>
    <evidence statement_id="3" type="irrelevant" version="0">
    </evidence>
    <evidence statement_id="4" type="irrelevant" version="0">
    </evidence>
    <evidence statement_id="5" type="irrelevant" version="0">
    </evidence>
    <evidence statement_id="6" type="relevant" version="0">
    </evidence>
    <evidence statement_id="7" type="relevant" version="0">
    </evidence>
    <evidence statement_id="8" type="relevant" version="0">
    </evidence>
    <evidence statement_id="9" type="relevant" version="0">
    </evidence>
   </cell>
  </row>
  <row row="4">
   <cell col-end="0" col-start="0" row-end="4" row-start="4" text="2013">
    <evidence statement_id="0" type="irrelevant" version="0">
    </evidence>
    <evidence statement_id="1" type="irrelevant" version="0">
    </evidence>
    <evidence statement_id="2" type="irrelevant" version="0">
    </evidence>
    <evidence statement_id="3" type="irrelevant" version="0">
    </evidence>
    <evidence statement_id="4" type="relevant" version="0">
    </evidence>
    <evidence statement_id="5" type="relevant" version="0">
    </evidence>
    <evidence statement_id="6" type="irrelevant" version="0">
    </evidence>
    <evidence statement_id="7" type="irrelevant" version="0">
    </evidence>
    <evidence statement_id="8" type="irrelevant" version="0">
    </evidence>
    <evidence statement_id="9" type="irrelevant" version="0">
    </evidence>
   </cell>
   <cell col-end="1" col-start="1" row-end="4" row-start="4" text="1.67%">
    <evidence statement_id="0" type="relevant" version="0">
    </evidence>
    <evidence statement_id="1" type="irrelevant" version="0">
    </evidence>
    <evidence statement_id="2" type="irrelevant" version="0">
    </evidence>
    <evidence statement_id="3" type="irrelevant" version="0">
    </evidence>
    <evidence statement_id="4" type="irrelevant" version="0">
    </evidence>
    <evidence statement_id="5" type="irrelevant" version="0">
    </evidence>
    <evidence statement_id="6" type="relevant" version="0">
    </evidence>
    <evidence statement_id="7" type="relevant" version="0">
    </evidence>
    <evidence statement_id="8" type="relevant" version="0">
    </evidence>
    <evidence statement_id="9" type="relevant" version="0">
    </evidence>
   </cell>
   <cell col-end="2" col-start="2" row-end="4" row-start="4" text="2018">
    <evidence statement_id="0" type="irrelevant" version="0">
    </evidence>
    <evidence statement_id="1" type="irrelevant" version="0">
    </evidence>
    <evidence statement_id="2" type="irrelevant" version="0">
    </evidence>
    <evidence statement_id="3" type="irrelevant" version="0">
    </evidence>
    <evidence statement_id="4" type="relevant" version="0">
    </evidence>
    <evidence statement_id="5" type="relevant" version="0">
    </evidence>
    <evidence statement_id="6" type="irrelevant" version="0">
    </evidence>
    <evidence statement_id="7" type="irrelevant" version="0">
    </evidence>
    <evidence statement_id="8" type="irrelevant" version="0">
    </evidence>
    <evidence statement_id="9" type="irrelevant" version="0">
    </evidence>
   </cell>
   <cell col-end="3" col-start="3" row-end="4" row-start="4" text="0.91%">
    <evidence statement_id="0" type="relevant" version="0">
    </evidence>
    <evidence statement_id="1" type="irrelevant" version="0">
    </evidence>
    <evidence statement_id="2" type="irrelevant" version="0">
    </evidence>
    <evidence statement_id="3" type="irrelevant" version="0">
    </evidence>
    <evidence statement_id="4" type="irrelevant" version="0">
    </evidence>
    <evidence statement_id="5" type="irrelevant" version="0">
    </evidence>
    <evidence statement_id="6" type="relevant" version="0">
    </evidence>
    <evidence statement_id="7" type="relevant" version="0">
    </evidence>
    <evidence statement_id="8" type="relevant" version="0">
    </evidence>
    <evidence statement_id="9" type="relevant" version="0">
    </evidence>
   </cell>
  </row>
  <row row="5">
   <cell col-end="0" col-start="0" row-end="5" row-start="5" text="2014">
    <evidence statement_id="0" type="irrelevant" version="0">
    </evidence>
    <evidence statement_id="1" type="irrelevant" version="0">
    </evidence>
    <evidence statement_id="2" type="irrelevant" version="0">
    </evidence>
    <evidence statement_id="3" type="irrelevant" version="0">
    </evidence>
    <evidence statement_id="4" type="relevant" version="0">
    </evidence>
    <evidence statement_id="5" type="relevant" version="0">
    </evidence>
    <evidence statement_id="6" type="irrelevant" version="0">
    </evidence>
    <evidence statement_id="7" type="irrelevant" version="0">
    </evidence>
    <evidence statement_id="8" type="irrelevant" version="0">
    </evidence>
    <evidence statement_id="9" type="irrelevant" version="0">
    </evidence>
   </cell>
   <cell col-end="1" col-start="1" row-end="5" row-start="5" text="1.52%">
    <evidence statement_id="0" type="relevant" version="0">
    </evidence>
    <evidence statement_id="1" type="irrelevant" version="0">
    </evidence>
    <evidence statement_id="2" type="irrelevant" version="0">
    </evidence>
    <evidence statement_id="3" type="irrelevant" version="0">
    </evidence>
    <evidence statement_id="4" type="irrelevant" version="0">
    </evidence>
    <evidence statement_id="5" type="irrelevant" version="0">
    </evidence>
    <evidence statement_id="6" type="relevant" version="0">
    </evidence>
    <evidence statement_id="7" type="relevant" version="0">
    </evidence>
    <evidence statement_id="8" type="relevant" version="0">
    </evidence>
    <evidence statement_id="9" type="relevant" version="0">
    </evidence>
   </cell>
   <cell col-end="2" col-start="2" row-end="5" row-start="5" text="2019">
    <evidence statement_id="0" type="irrelevant" version="0">
    </evidence>
    <evidence statement_id="1" type="relevant" version="0">
    </evidence>
    <evidence statement_id="2" type="irrelevant" version="0">
    </evidence>
    <evidence statement_id="3" type="irrelevant" version="0">
    </evidence>
    <evidence statement_id="4" type="relevant" version="0">
    </evidence>
    <evidence statement_id="5" type="relevant" version="0">
    </evidence>
    <evidence statement_id="6" type="irrelevant" version="0">
    </evidence>
    <evidence statement_id="7" type="irrelevant" version="0">
    </evidence>
    <evidence statement_id="8" type="irrelevant" version="0">
    </evidence>
    <evidence statement_id="9" type="relevant" version="0">
    </evidence>
   </cell>
   <cell col-end="3" col-start="3" row-end="5" row-start="5" text="0.67%">
    <evidence statement_id="0" type="relevant" version="0">
    </evidence>
    <evidence statement_id="1" type="relevant" version="0">
    </evidence>
    <evidence statement_id="2" type="irrelevant" version="0">
    </evidence>
    <evidence statement_id="3" type="irrelevant" version="0">
    </evidence>
    <evidence statement_id="4" type="irrelevant" version="0">
    </evidence>
    <evidence statement_id="5" type="irrelevant" version="0">
    </evidence>
    <evidence statement_id="6" type="relevant" version="0">
    </evidence>
    <evidence statement_id="7" type="relevant" version="0">
    </evidence>
    <evidence statement_id="8" type="relevant" version="0">
    </evidence>
    <evidence statement_id="9" type="relevant" version="0">
    </evidence>
   </cell>
  </row>
  <statements>
   <statement id="0" text="Some of the measurement errors (ME) are negative." type="refuted">
   </statement>
   <statement id="1" text="The highest measurement error (ME) is 0.94% in the year 2019." type="refuted">
   </statement>
   <statement id="2" text="The lowest measurement error (ME) is 7.50% in the year 2016." type="refuted">
   </statement>
   <statement id="3" text="The years 2010 and 2015 have the same measurement errors." type="refuted">
   </statement>
   <statement id="4" text="The years range from 2010 to 2020." type="refuted">
   </statement>
   <statement id="5" text="The year ranges from 2010 to 2019." type="entailed">
   </statement>
   <statement id="6" text="Each year consist of different measurement errors." type="entailed">
   </statement>
   <statement id="7" text="The highest measurement error is 9.50% in the year 2016." type="entailed">
   </statement>
   <statement id="8" text="All the measurement errors are in positive." type="entailed">
   </statement>
   <statement id="9" text="The lowest measurement error is 0.67 % in the year 2019." type="entailed">
   </statement>
   <statement id="10" text="and therefore it covers many fewer trade inflows into Russia than the BACI dataset." type="unknown">
   </statement>
  </statements>
 </table>
</document>