<document>
 <table id="Table 1">
  <caption text="

   Summary of the main features of the different cases of creative tourism.
  
">
  </caption>
  <row row="0">
   <cell col-end="0" col-start="0" row-end="1" row-start="0" text="Context">
    <evidence statement_id="0" type="" version="">
    </evidence>
    <evidence statement_id="1" type="" version="">
    </evidence>
    <evidence statement_id="2" type="" version="">
    </evidence>
    <evidence statement_id="3" type="" version="">
    </evidence>
    <evidence statement_id="4" type="" version="">
    </evidence>
    <evidence statement_id="5" type="" version="">
    </evidence>
    <evidence statement_id="6" type="" version="">
    </evidence>
    <evidence statement_id="7" type="" version="">
    </evidence>
    <evidence statement_id="8" type="" version="">
    </evidence>
    <evidence statement_id="9" type="" version="">
    </evidence>
    <evidence statement_id="10" type="" version="">
    </evidence>
   </cell>
   <cell col-end="3" col-start="1" row-end="0" row-start="0" text="Preparation phase">
    <evidence statement_id="0" type="" version="">
    </evidence>
    <evidence statement_id="1" type="" version="">
    </evidence>
    <evidence statement_id="2" type="" version="">
    </evidence>
    <evidence statement_id="3" type="" version="">
    </evidence>
    <evidence statement_id="4" type="" version="">
    </evidence>
    <evidence statement_id="5" type="" version="">
    </evidence>
    <evidence statement_id="6" type="" version="">
    </evidence>
    <evidence statement_id="7" type="" version="">
    </evidence>
    <evidence statement_id="8" type="" version="">
    </evidence>
    <evidence statement_id="9" type="" version="">
    </evidence>
    <evidence statement_id="10" type="" version="">
    </evidence>
   </cell>
   <cell col-end="6" col-start="4" row-end="0" row-start="0" text="Implementation phase">
    <evidence statement_id="0" type="" version="">
    </evidence>
    <evidence statement_id="1" type="" version="">
    </evidence>
    <evidence statement_id="2" type="" version="">
    </evidence>
    <evidence statement_id="3" type="" version="">
    </evidence>
    <evidence statement_id="4" type="" version="">
    </evidence>
    <evidence statement_id="5" type="" version="">
    </evidence>
    <evidence statement_id="6" type="" version="">
    </evidence>
    <evidence statement_id="7" type="" version="">
    </evidence>
    <evidence statement_id="8" type="" version="">
    </evidence>
    <evidence statement_id="9" type="" version="">
    </evidence>
    <evidence statement_id="10" type="" version="">
    </evidence>
   </cell>
   <cell col-end="7" col-start="7" row-end="1" row-start="0" text="Related literature">
    <evidence statement_id="0" type="" version="">
    </evidence>
    <evidence statement_id="1" type="" version="">
    </evidence>
    <evidence statement_id="2" type="" version="">
    </evidence>
    <evidence statement_id="3" type="" version="">
    </evidence>
    <evidence statement_id="4" type="" version="">
    </evidence>
    <evidence statement_id="5" type="" version="">
    </evidence>
    <evidence statement_id="6" type="" version="">
    </evidence>
    <evidence statement_id="7" type="" version="">
    </evidence>
    <evidence statement_id="8" type="" version="">
    </evidence>
    <evidence statement_id="9" type="" version="">
    </evidence>
    <evidence statement_id="10" type="" version="">
    </evidence>
   </cell>
  </row>
  <row row="1">
   <cell col-end="1" col-start="1" row-end="1" row-start="1" text="Inspiration">
    <evidence statement_id="0" type="" version="">
    </evidence>
    <evidence statement_id="1" type="" version="">
    </evidence>
    <evidence statement_id="2" type="" version="">
    </evidence>
    <evidence statement_id="3" type="" version="">
    </evidence>
    <evidence statement_id="4" type="" version="">
    </evidence>
    <evidence statement_id="5" type="" version="">
    </evidence>
    <evidence statement_id="6" type="" version="">
    </evidence>
    <evidence statement_id="7" type="" version="">
    </evidence>
    <evidence statement_id="8" type="" version="">
    </evidence>
    <evidence statement_id="9" type="" version="">
    </evidence>
    <evidence statement_id="10" type="" version="">
    </evidence>
   </cell>
   <cell col-end="2" col-start="2" row-end="1" row-start="1" text="Selection">
    <evidence statement_id="0" type="" version="">
    </evidence>
    <evidence statement_id="1" type="" version="">
    </evidence>
    <evidence statement_id="2" type="" version="">
    </evidence>
    <evidence statement_id="3" type="" version="">
    </evidence>
    <evidence statement_id="4" type="" version="">
    </evidence>
    <evidence statement_id="5" type="" version="">
    </evidence>
    <evidence statement_id="6" type="" version="">
    </evidence>
    <evidence statement_id="7" type="" version="">
    </evidence>
    <evidence statement_id="8" type="" version="">
    </evidence>
    <evidence statement_id="9" type="" version="">
    </evidence>
    <evidence statement_id="10" type="" version="">
    </evidence>
   </cell>
   <cell col-end="3" col-start="3" row-end="1" row-start="1" text="Structure">
    <evidence statement_id="0" type="" version="">
    </evidence>
    <evidence statement_id="1" type="" version="">
    </evidence>
    <evidence statement_id="2" type="" version="">
    </evidence>
    <evidence statement_id="3" type="" version="">
    </evidence>
    <evidence statement_id="4" type="" version="">
    </evidence>
    <evidence statement_id="5" type="" version="">
    </evidence>
    <evidence statement_id="6" type="" version="">
    </evidence>
    <evidence statement_id="7" type="" version="">
    </evidence>
    <evidence statement_id="8" type="" version="">
    </evidence>
    <evidence statement_id="9" type="" version="">
    </evidence>
    <evidence statement_id="10" type="" version="">
    </evidence>
   </cell>
   <cell col-end="4" col-start="4" row-end="1" row-start="1" text="Mobilizing resources">
    <evidence statement_id="0" type="" version="">
    </evidence>
    <evidence statement_id="1" type="" version="">
    </evidence>
    <evidence statement_id="2" type="" version="">
    </evidence>
    <evidence statement_id="3" type="" version="">
    </evidence>
    <evidence statement_id="4" type="" version="">
    </evidence>
    <evidence statement_id="5" type="" version="">
    </evidence>
    <evidence statement_id="6" type="" version="">
    </evidence>
    <evidence statement_id="7" type="" version="">
    </evidence>
    <evidence statement_id="8" type="" version="">
    </evidence>
    <evidence statement_id="9" type="" version="">
    </evidence>
    <evidence statement_id="10" type="" version="">
    </evidence>
   </cell>
   <cell col-end="5" col-start="5" row-end="1" row-start="1" text="Meanings">
    <evidence statement_id="0" type="" version="">
    </evidence>
    <evidence statement_id="1" type="" version="">
    </evidence>
    <evidence statement_id="2" type="" version="">
    </evidence>
    <evidence statement_id="3" type="" version="">
    </evidence>
    <evidence statement_id="4" type="" version="">
    </evidence>
    <evidence statement_id="5" type="" version="">
    </evidence>
    <evidence statement_id="6" type="" version="">
    </evidence>
    <evidence statement_id="7" type="" version="">
    </evidence>
    <evidence statement_id="8" type="" version="">
    </evidence>
    <evidence statement_id="9" type="" version="">
    </evidence>
    <evidence statement_id="10" type="" version="">
    </evidence>
   </cell>
   <cell col-end="6" col-start="6" row-end="1" row-start="1" text="Creativities">
    <evidence statement_id="0" type="" version="">
    </evidence>
    <evidence statement_id="1" type="" version="">
    </evidence>
    <evidence statement_id="2" type="" version="">
    </evidence>
    <evidence statement_id="3" type="" version="">
    </evidence>
    <evidence statement_id="4" type="" version="">
    </evidence>
    <evidence statement_id="5" type="" version="">
    </evidence>
    <evidence statement_id="6" type="" version="">
    </evidence>
    <evidence statement_id="7" type="" version="">
    </evidence>
    <evidence statement_id="8" type="" version="">
    </evidence>
    <evidence statement_id="9" type="" version="">
    </evidence>
    <evidence statement_id="10" type="" version="">
    </evidence>
   </cell>
  </row>
  <row row="2">
   <cell col-end="0" col-start="0" row-end="2" row-start="2" text="Rural areas (Thailand)">
    <evidence statement_id="0" type="" version="">
    </evidence>
    <evidence statement_id="1" type="" version="">
    </evidence>
    <evidence statement_id="2" type="" version="">
    </evidence>
    <evidence statement_id="3" type="" version="">
    </evidence>
    <evidence statement_id="4" type="" version="">
    </evidence>
    <evidence statement_id="5" type="" version="">
    </evidence>
    <evidence statement_id="6" type="" version="">
    </evidence>
    <evidence statement_id="7" type="" version="">
    </evidence>
    <evidence statement_id="8" type="" version="">
    </evidence>
    <evidence statement_id="9" type="" version="">
    </evidence>
    <evidence statement_id="10" type="" version="">
    </evidence>
   </cell>
   <cell col-end="1" col-start="1" row-end="2" row-start="2" text="Authenticity, local crafts and ‘Thainess’">
    <evidence statement_id="0" type="" version="">
    </evidence>
    <evidence statement_id="1" type="" version="">
    </evidence>
    <evidence statement_id="2" type="" version="">
    </evidence>
    <evidence statement_id="3" type="" version="">
    </evidence>
    <evidence statement_id="4" type="" version="">
    </evidence>
    <evidence statement_id="5" type="" version="">
    </evidence>
    <evidence statement_id="6" type="" version="">
    </evidence>
    <evidence statement_id="7" type="" version="">
    </evidence>
    <evidence statement_id="8" type="" version="">
    </evidence>
    <evidence statement_id="9" type="" version="">
    </evidence>
    <evidence statement_id="10" type="" version="">
    </evidence>
   </cell>
   <cell col-end="2" col-start="2" row-end="2" row-start="2" text="Community-based discussions and appreciative inquiry.">
    <evidence statement_id="0" type="" version="">
    </evidence>
    <evidence statement_id="1" type="" version="">
    </evidence>
    <evidence statement_id="2" type="" version="">
    </evidence>
    <evidence statement_id="3" type="" version="">
    </evidence>
    <evidence statement_id="4" type="" version="">
    </evidence>
    <evidence statement_id="5" type="" version="">
    </evidence>
    <evidence statement_id="6" type="" version="">
    </evidence>
    <evidence statement_id="7" type="" version="">
    </evidence>
    <evidence statement_id="8" type="" version="">
    </evidence>
    <evidence statement_id="9" type="" version="">
    </evidence>
    <evidence statement_id="10" type="" version="">
    </evidence>
   </cell>
   <cell col-end="3" col-start="3" row-end="2" row-start="2" text="Top-down policies implemented with community involvement">
    <evidence statement_id="0" type="" version="">
    </evidence>
    <evidence statement_id="1" type="" version="">
    </evidence>
    <evidence statement_id="2" type="" version="">
    </evidence>
    <evidence statement_id="3" type="" version="">
    </evidence>
    <evidence statement_id="4" type="" version="">
    </evidence>
    <evidence statement_id="5" type="" version="">
    </evidence>
    <evidence statement_id="6" type="" version="">
    </evidence>
    <evidence statement_id="7" type="" version="">
    </evidence>
    <evidence statement_id="8" type="" version="">
    </evidence>
    <evidence statement_id="9" type="" version="">
    </evidence>
    <evidence statement_id="10" type="" version="">
    </evidence>
   </cell>
   <cell col-end="4" col-start="4" row-end="2" row-start="2" text="Local crafts, traditional skills, use of natural products, creativity of individual craftspeople">
    <evidence statement_id="0" type="" version="">
    </evidence>
    <evidence statement_id="1" type="" version="">
    </evidence>
    <evidence statement_id="2" type="" version="">
    </evidence>
    <evidence statement_id="3" type="" version="">
    </evidence>
    <evidence statement_id="4" type="" version="">
    </evidence>
    <evidence statement_id="5" type="" version="">
    </evidence>
    <evidence statement_id="6" type="" version="">
    </evidence>
    <evidence statement_id="7" type="" version="">
    </evidence>
    <evidence statement_id="8" type="" version="">
    </evidence>
    <evidence statement_id="9" type="" version="">
    </evidence>
    <evidence statement_id="10" type="" version="">
    </evidence>
   </cell>
   <cell col-end="5" col-start="5" row-end="2" row-start="2" text="Community life, relationship to nature, tradition, sustainability">
    <evidence statement_id="0" type="" version="">
    </evidence>
    <evidence statement_id="1" type="" version="">
    </evidence>
    <evidence statement_id="2" type="" version="">
    </evidence>
    <evidence statement_id="3" type="" version="">
    </evidence>
    <evidence statement_id="4" type="" version="">
    </evidence>
    <evidence statement_id="5" type="" version="">
    </evidence>
    <evidence statement_id="6" type="" version="">
    </evidence>
    <evidence statement_id="7" type="" version="">
    </evidence>
    <evidence statement_id="8" type="" version="">
    </evidence>
    <evidence statement_id="9" type="" version="">
    </evidence>
    <evidence statement_id="10" type="" version="">
    </evidence>
   </cell>
   <cell col-end="6" col-start="6" row-end="2" row-start="2" text="Giving new life to tradition through experience design, improving livelihoods, linking to the tourist economy.">
    <evidence statement_id="0" type="" version="">
    </evidence>
    <evidence statement_id="1" type="" version="">
    </evidence>
    <evidence statement_id="2" type="" version="">
    </evidence>
    <evidence statement_id="3" type="" version="">
    </evidence>
    <evidence statement_id="4" type="" version="">
    </evidence>
    <evidence statement_id="5" type="" version="">
    </evidence>
    <evidence statement_id="6" type="" version="">
    </evidence>
    <evidence statement_id="7" type="" version="">
    </evidence>
    <evidence statement_id="8" type="" version="">
    </evidence>
    <evidence statement_id="9" type="" version="">
    </evidence>
    <evidence statement_id="10" type="" version="">
    </evidence>
   </cell>
   <cell col-end="7" col-start="7" row-end="2" row-start="2" text="Brouder (2012)
     
     ;
     
      Blapp and Mitas (2019)">
    <evidence statement_id="0" type="" version="">
    </evidence>
    <evidence statement_id="1" type="" version="">
    </evidence>
    <evidence statement_id="2" type="" version="">
    </evidence>
    <evidence statement_id="3" type="" version="">
    </evidence>
    <evidence statement_id="4" type="" version="">
    </evidence>
    <evidence statement_id="5" type="" version="">
    </evidence>
    <evidence statement_id="6" type="" version="">
    </evidence>
    <evidence statement_id="7" type="" version="">
    </evidence>
    <evidence statement_id="8" type="" version="">
    </evidence>
    <evidence statement_id="9" type="" version="">
    </evidence>
    <evidence statement_id="10" type="" version="">
    </evidence>
   </cell>
  </row>
  <row row="3">
   <cell col-end="0" col-start="0" row-end="3" row-start="3" text="Small cities (Den Bosch)">
    <evidence statement_id="0" type="" version="">
    </evidence>
    <evidence statement_id="1" type="" version="">
    </evidence>
    <evidence statement_id="2" type="" version="">
    </evidence>
    <evidence statement_id="3" type="" version="">
    </evidence>
    <evidence statement_id="4" type="" version="">
    </evidence>
    <evidence statement_id="5" type="" version="">
    </evidence>
    <evidence statement_id="6" type="" version="">
    </evidence>
    <evidence statement_id="7" type="" version="">
    </evidence>
    <evidence statement_id="8" type="" version="">
    </evidence>
    <evidence statement_id="9" type="" version="">
    </evidence>
    <evidence statement_id="10" type="" version="">
    </evidence>
   </cell>
   <cell col-end="1" col-start="1" row-end="3" row-start="3" text="Iconic artist as basis for programme development">
    <evidence statement_id="0" type="" version="">
    </evidence>
    <evidence statement_id="1" type="" version="">
    </evidence>
    <evidence statement_id="2" type="" version="">
    </evidence>
    <evidence statement_id="3" type="" version="">
    </evidence>
    <evidence statement_id="4" type="" version="">
    </evidence>
    <evidence statement_id="5" type="" version="">
    </evidence>
    <evidence statement_id="6" type="" version="">
    </evidence>
    <evidence statement_id="7" type="" version="">
    </evidence>
    <evidence statement_id="8" type="" version="">
    </evidence>
    <evidence statement_id="9" type="" version="">
    </evidence>
    <evidence statement_id="10" type="" version="">
    </evidence>
   </cell>
   <cell col-end="2" col-start="2" row-end="3" row-start="3" text="Artistic Director supported by a team of experts.">
    <evidence statement_id="0" type="" version="">
    </evidence>
    <evidence statement_id="1" type="" version="">
    </evidence>
    <evidence statement_id="2" type="" version="">
    </evidence>
    <evidence statement_id="3" type="" version="">
    </evidence>
    <evidence statement_id="4" type="" version="">
    </evidence>
    <evidence statement_id="5" type="" version="">
    </evidence>
    <evidence statement_id="6" type="" version="">
    </evidence>
    <evidence statement_id="7" type="" version="">
    </evidence>
    <evidence statement_id="8" type="" version="">
    </evidence>
    <evidence statement_id="9" type="" version="">
    </evidence>
    <evidence statement_id="10" type="" version="">
    </evidence>
   </cell>
   <cell col-end="3" col-start="3" row-end="3" row-start="3" text="Mayor as inspirational switcher, local government funding.">
    <evidence statement_id="0" type="" version="">
    </evidence>
    <evidence statement_id="1" type="" version="">
    </evidence>
    <evidence statement_id="2" type="" version="">
    </evidence>
    <evidence statement_id="3" type="" version="">
    </evidence>
    <evidence statement_id="4" type="" version="">
    </evidence>
    <evidence statement_id="5" type="" version="">
    </evidence>
    <evidence statement_id="6" type="" version="">
    </evidence>
    <evidence statement_id="7" type="" version="">
    </evidence>
    <evidence statement_id="8" type="" version="">
    </evidence>
    <evidence statement_id="9" type="" version="">
    </evidence>
    <evidence statement_id="10" type="" version="">
    </evidence>
   </cell>
   <cell col-end="4" col-start="4" row-end="3" row-start="3" text="Linking external and internal networks, local knowledge, cultural heritage">
    <evidence statement_id="0" type="" version="">
    </evidence>
    <evidence statement_id="1" type="" version="">
    </evidence>
    <evidence statement_id="2" type="" version="">
    </evidence>
    <evidence statement_id="3" type="" version="">
    </evidence>
    <evidence statement_id="4" type="" version="">
    </evidence>
    <evidence statement_id="5" type="" version="">
    </evidence>
    <evidence statement_id="6" type="" version="">
    </evidence>
    <evidence statement_id="7" type="" version="">
    </evidence>
    <evidence statement_id="8" type="" version="">
    </evidence>
    <evidence statement_id="9" type="" version="">
    </evidence>
    <evidence statement_id="10" type="" version="">
    </evidence>
   </cell>
   <cell col-end="5" col-start="5" row-end="3" row-start="3" text="Iconic figures, injecting creativity into heritage, using the underdog position relative to bigger cities">
    <evidence statement_id="0" type="" version="">
    </evidence>
    <evidence statement_id="1" type="" version="">
    </evidence>
    <evidence statement_id="2" type="" version="">
    </evidence>
    <evidence statement_id="3" type="" version="">
    </evidence>
    <evidence statement_id="4" type="" version="">
    </evidence>
    <evidence statement_id="5" type="" version="">
    </evidence>
    <evidence statement_id="6" type="" version="">
    </evidence>
    <evidence statement_id="7" type="" version="">
    </evidence>
    <evidence statement_id="8" type="" version="">
    </evidence>
    <evidence statement_id="9" type="" version="">
    </evidence>
    <evidence statement_id="10" type="" version="">
    </evidence>
   </cell>
   <cell col-end="6" col-start="6" row-end="3" row-start="3" text="Putting the city on the map, linking to the space of flows through collaboration with other cities.">
    <evidence statement_id="0" type="" version="">
    </evidence>
    <evidence statement_id="1" type="" version="">
    </evidence>
    <evidence statement_id="2" type="" version="">
    </evidence>
    <evidence statement_id="3" type="" version="">
    </evidence>
    <evidence statement_id="4" type="" version="">
    </evidence>
    <evidence statement_id="5" type="" version="">
    </evidence>
    <evidence statement_id="6" type="" version="">
    </evidence>
    <evidence statement_id="7" type="" version="">
    </evidence>
    <evidence statement_id="8" type="" version="">
    </evidence>
    <evidence statement_id="9" type="" version="">
    </evidence>
    <evidence statement_id="10" type="" version="">
    </evidence>
   </cell>
   <cell col-end="7" col-start="7" row-end="3" row-start="3" text="Richards and Duif (2018)
     
     ;
     
      Lorentzen and van Heur (2012)
     
     .">
    <evidence statement_id="0" type="" version="">
    </evidence>
    <evidence statement_id="1" type="" version="">
    </evidence>
    <evidence statement_id="2" type="" version="">
    </evidence>
    <evidence statement_id="3" type="" version="">
    </evidence>
    <evidence statement_id="4" type="" version="">
    </evidence>
    <evidence statement_id="5" type="" version="">
    </evidence>
    <evidence statement_id="6" type="" version="">
    </evidence>
    <evidence statement_id="7" type="" version="">
    </evidence>
    <evidence statement_id="8" type="" version="">
    </evidence>
    <evidence statement_id="9" type="" version="">
    </evidence>
    <evidence statement_id="10" type="" version="">
    </evidence>
   </cell>
  </row>
  <row row="4">
   <cell col-end="0" col-start="0" row-end="4" row-start="4" text="Large cities (Recife)">
    <evidence statement_id="0" type="" version="">
    </evidence>
    <evidence statement_id="1" type="" version="">
    </evidence>
    <evidence statement_id="2" type="" version="">
    </evidence>
    <evidence statement_id="3" type="" version="">
    </evidence>
    <evidence statement_id="4" type="" version="">
    </evidence>
    <evidence statement_id="5" type="" version="">
    </evidence>
    <evidence statement_id="6" type="" version="">
    </evidence>
    <evidence statement_id="7" type="" version="">
    </evidence>
    <evidence statement_id="8" type="" version="">
    </evidence>
    <evidence statement_id="9" type="" version="">
    </evidence>
    <evidence statement_id="10" type="" version="">
    </evidence>
   </cell>
   <cell col-end="1" col-start="1" row-end="4" row-start="4" text="Distinctive popular culture (Carnival, Frevo)">
    <evidence statement_id="0" type="" version="">
    </evidence>
    <evidence statement_id="1" type="" version="">
    </evidence>
    <evidence statement_id="2" type="" version="">
    </evidence>
    <evidence statement_id="3" type="" version="">
    </evidence>
    <evidence statement_id="4" type="" version="">
    </evidence>
    <evidence statement_id="5" type="" version="">
    </evidence>
    <evidence statement_id="6" type="" version="">
    </evidence>
    <evidence statement_id="7" type="" version="">
    </evidence>
    <evidence statement_id="8" type="" version="">
    </evidence>
    <evidence statement_id="9" type="" version="">
    </evidence>
    <evidence statement_id="10" type="" version="">
    </evidence>
   </cell>
   <cell col-end="2" col-start="2" row-end="4" row-start="4" text="Hackathons, immersion labs and workshops with a broad range of stakeholders">
    <evidence statement_id="0" type="" version="">
    </evidence>
    <evidence statement_id="1" type="" version="">
    </evidence>
    <evidence statement_id="2" type="" version="">
    </evidence>
    <evidence statement_id="3" type="" version="">
    </evidence>
    <evidence statement_id="4" type="" version="">
    </evidence>
    <evidence statement_id="5" type="" version="">
    </evidence>
    <evidence statement_id="6" type="" version="">
    </evidence>
    <evidence statement_id="7" type="" version="">
    </evidence>
    <evidence statement_id="8" type="" version="">
    </evidence>
    <evidence statement_id="9" type="" version="">
    </evidence>
    <evidence statement_id="10" type="" version="">
    </evidence>
   </cell>
   <cell col-end="3" col-start="3" row-end="4" row-start="4" text="Public-private collaboration, with involvement of civic groups.">
    <evidence statement_id="0" type="" version="">
    </evidence>
    <evidence statement_id="1" type="" version="">
    </evidence>
    <evidence statement_id="2" type="" version="">
    </evidence>
    <evidence statement_id="3" type="" version="">
    </evidence>
    <evidence statement_id="4" type="" version="">
    </evidence>
    <evidence statement_id="5" type="" version="">
    </evidence>
    <evidence statement_id="6" type="" version="">
    </evidence>
    <evidence statement_id="7" type="" version="">
    </evidence>
    <evidence statement_id="8" type="" version="">
    </evidence>
    <evidence statement_id="9" type="" version="">
    </evidence>
    <evidence statement_id="10" type="" version="">
    </evidence>
   </cell>
   <cell col-end="4" col-start="4" row-end="4" row-start="4" text="Creative industries, popular culture, neighbourhoods, creative clusters, creative class">
    <evidence statement_id="0" type="" version="">
    </evidence>
    <evidence statement_id="1" type="" version="">
    </evidence>
    <evidence statement_id="2" type="" version="">
    </evidence>
    <evidence statement_id="3" type="" version="">
    </evidence>
    <evidence statement_id="4" type="" version="">
    </evidence>
    <evidence statement_id="5" type="" version="">
    </evidence>
    <evidence statement_id="6" type="" version="">
    </evidence>
    <evidence statement_id="7" type="" version="">
    </evidence>
    <evidence statement_id="8" type="" version="">
    </evidence>
    <evidence statement_id="9" type="" version="">
    </evidence>
    <evidence statement_id="10" type="" version="">
    </evidence>
   </cell>
   <cell col-end="5" col-start="5" row-end="4" row-start="4" text="Diversity, cultural vibrancy, social cohesion, new urban rituals">
    <evidence statement_id="0" type="" version="">
    </evidence>
    <evidence statement_id="1" type="" version="">
    </evidence>
    <evidence statement_id="2" type="" version="">
    </evidence>
    <evidence statement_id="3" type="" version="">
    </evidence>
    <evidence statement_id="4" type="" version="">
    </evidence>
    <evidence statement_id="5" type="" version="">
    </evidence>
    <evidence statement_id="6" type="" version="">
    </evidence>
    <evidence statement_id="7" type="" version="">
    </evidence>
    <evidence statement_id="8" type="" version="">
    </evidence>
    <evidence statement_id="9" type="" version="">
    </evidence>
    <evidence statement_id="10" type="" version="">
    </evidence>
   </cell>
   <cell col-end="6" col-start="6" row-end="4" row-start="4" text="Playfulness, new technologies, smart city">
    <evidence statement_id="0" type="" version="">
    </evidence>
    <evidence statement_id="1" type="" version="">
    </evidence>
    <evidence statement_id="2" type="" version="">
    </evidence>
    <evidence statement_id="3" type="" version="">
    </evidence>
    <evidence statement_id="4" type="" version="">
    </evidence>
    <evidence statement_id="5" type="" version="">
    </evidence>
    <evidence statement_id="6" type="" version="">
    </evidence>
    <evidence statement_id="7" type="" version="">
    </evidence>
    <evidence statement_id="8" type="" version="">
    </evidence>
    <evidence statement_id="9" type="" version="">
    </evidence>
    <evidence statement_id="10" type="" version="">
    </evidence>
   </cell>
   <cell col-end="7" col-start="7" row-end="4" row-start="4" text="Florida (2002)
     
     ;
     
      Landry (2012)
     
     ;
     
      Richards (2014)
     
     .">
    <evidence statement_id="0" type="" version="">
    </evidence>
    <evidence statement_id="1" type="" version="">
    </evidence>
    <evidence statement_id="2" type="" version="">
    </evidence>
    <evidence statement_id="3" type="" version="">
    </evidence>
    <evidence statement_id="4" type="" version="">
    </evidence>
    <evidence statement_id="5" type="" version="">
    </evidence>
    <evidence statement_id="6" type="" version="">
    </evidence>
    <evidence statement_id="7" type="" version="">
    </evidence>
    <evidence statement_id="8" type="" version="">
    </evidence>
    <evidence statement_id="9" type="" version="">
    </evidence>
    <evidence statement_id="10" type="" version="">
    </evidence>
   </cell>
  </row>
  <row row="5">
   <cell col-end="0" col-start="0" row-end="5" row-start="5" text="Conurbations (Nordrhein-Westfalen)">
    <evidence statement_id="0" type="" version="">
    </evidence>
    <evidence statement_id="1" type="" version="">
    </evidence>
    <evidence statement_id="2" type="" version="">
    </evidence>
    <evidence statement_id="3" type="" version="">
    </evidence>
    <evidence statement_id="4" type="" version="">
    </evidence>
    <evidence statement_id="5" type="" version="">
    </evidence>
    <evidence statement_id="6" type="" version="">
    </evidence>
    <evidence statement_id="7" type="" version="">
    </evidence>
    <evidence statement_id="8" type="" version="">
    </evidence>
    <evidence statement_id="9" type="" version="">
    </evidence>
    <evidence statement_id="10" type="" version="">
    </evidence>
   </cell>
   <cell col-end="1" col-start="1" row-end="5" row-start="5" text="Diverse creative scene with strengths in music, media art, street art and literature">
    <evidence statement_id="0" type="" version="">
    </evidence>
    <evidence statement_id="1" type="" version="">
    </evidence>
    <evidence statement_id="2" type="" version="">
    </evidence>
    <evidence statement_id="3" type="" version="">
    </evidence>
    <evidence statement_id="4" type="" version="">
    </evidence>
    <evidence statement_id="5" type="" version="">
    </evidence>
    <evidence statement_id="6" type="" version="">
    </evidence>
    <evidence statement_id="7" type="" version="">
    </evidence>
    <evidence statement_id="8" type="" version="">
    </evidence>
    <evidence statement_id="9" type="" version="">
    </evidence>
    <evidence statement_id="10" type="" version="">
    </evidence>
   </cell>
   <cell col-end="2" col-start="2" row-end="5" row-start="5" text="Project team with input from individual makers">
    <evidence statement_id="0" type="" version="">
    </evidence>
    <evidence statement_id="1" type="" version="">
    </evidence>
    <evidence statement_id="2" type="" version="">
    </evidence>
    <evidence statement_id="3" type="" version="">
    </evidence>
    <evidence statement_id="4" type="" version="">
    </evidence>
    <evidence statement_id="5" type="" version="">
    </evidence>
    <evidence statement_id="6" type="" version="">
    </evidence>
    <evidence statement_id="7" type="" version="">
    </evidence>
    <evidence statement_id="8" type="" version="">
    </evidence>
    <evidence statement_id="9" type="" version="">
    </evidence>
    <evidence statement_id="10" type="" version="">
    </evidence>
   </cell>
   <cell col-end="3" col-start="3" row-end="5" row-start="5" text="European Union supported project run by regional government and tourist board">
    <evidence statement_id="0" type="" version="">
    </evidence>
    <evidence statement_id="1" type="" version="">
    </evidence>
    <evidence statement_id="2" type="" version="">
    </evidence>
    <evidence statement_id="3" type="" version="">
    </evidence>
    <evidence statement_id="4" type="" version="">
    </evidence>
    <evidence statement_id="5" type="" version="">
    </evidence>
    <evidence statement_id="6" type="" version="">
    </evidence>
    <evidence statement_id="7" type="" version="">
    </evidence>
    <evidence statement_id="8" type="" version="">
    </evidence>
    <evidence statement_id="9" type="" version="">
    </evidence>
    <evidence statement_id="10" type="" version="">
    </evidence>
   </cell>
   <cell col-end="4" col-start="4" row-end="5" row-start="5" text="Creative economy, cosmopolitan atmosphere, creative cities">
    <evidence statement_id="0" type="" version="">
    </evidence>
    <evidence statement_id="1" type="" version="">
    </evidence>
    <evidence statement_id="2" type="" version="">
    </evidence>
    <evidence statement_id="3" type="" version="">
    </evidence>
    <evidence statement_id="4" type="" version="">
    </evidence>
    <evidence statement_id="5" type="" version="">
    </evidence>
    <evidence statement_id="6" type="" version="">
    </evidence>
    <evidence statement_id="7" type="" version="">
    </evidence>
    <evidence statement_id="8" type="" version="">
    </evidence>
    <evidence statement_id="9" type="" version="">
    </evidence>
    <evidence statement_id="10" type="" version="">
    </evidence>
   </cell>
   <cell col-end="5" col-start="5" row-end="5" row-start="5" text="Authenticity related to gritty industrial past, eclectic, idiosyncratic, exploring the urban jungle">
    <evidence statement_id="0" type="" version="">
    </evidence>
    <evidence statement_id="1" type="" version="">
    </evidence>
    <evidence statement_id="2" type="" version="">
    </evidence>
    <evidence statement_id="3" type="" version="">
    </evidence>
    <evidence statement_id="4" type="" version="">
    </evidence>
    <evidence statement_id="5" type="" version="">
    </evidence>
    <evidence statement_id="6" type="" version="">
    </evidence>
    <evidence statement_id="7" type="" version="">
    </evidence>
    <evidence statement_id="8" type="" version="">
    </evidence>
    <evidence statement_id="9" type="" version="">
    </evidence>
    <evidence statement_id="10" type="" version="">
    </evidence>
   </cell>
   <cell col-end="6" col-start="6" row-end="5" row-start="5" text="Stories as linking devices between the nodes of the conurbation, post-tourism, framing the inauthentic, cultural scenes">
    <evidence statement_id="0" type="" version="">
    </evidence>
    <evidence statement_id="1" type="" version="">
    </evidence>
    <evidence statement_id="2" type="" version="">
    </evidence>
    <evidence statement_id="3" type="" version="">
    </evidence>
    <evidence statement_id="4" type="" version="">
    </evidence>
    <evidence statement_id="5" type="" version="">
    </evidence>
    <evidence statement_id="6" type="" version="">
    </evidence>
    <evidence statement_id="7" type="" version="">
    </evidence>
    <evidence statement_id="8" type="" version="">
    </evidence>
    <evidence statement_id="9" type="" version="">
    </evidence>
    <evidence statement_id="10" type="" version="">
    </evidence>
   </cell>
   <cell col-end="7" col-start="7" row-end="5" row-start="5" text="Richards and Wilson (2007)
     
     ;
     
      Sacco and Blessi (2007)
     
     ;
     
      Zukin (1995)">
    <evidence statement_id="0" type="" version="">
    </evidence>
    <evidence statement_id="1" type="" version="">
    </evidence>
    <evidence statement_id="2" type="" version="">
    </evidence>
    <evidence statement_id="3" type="" version="">
    </evidence>
    <evidence statement_id="4" type="" version="">
    </evidence>
    <evidence statement_id="5" type="" version="">
    </evidence>
    <evidence statement_id="6" type="" version="">
    </evidence>
    <evidence statement_id="7" type="" version="">
    </evidence>
    <evidence statement_id="8" type="" version="">
    </evidence>
    <evidence statement_id="9" type="" version="">
    </evidence>
    <evidence statement_id="10" type="" version="">
    </evidence>
   </cell>
  </row>
  <statements>
   <statement id="0" text="Conurbations in Nordrhein-Westfalen selects to Project individual with input from group makers." type="">
   </statement>
   <statement id="1" text="The table contains 4 types of phase." type="">
   </statement>
   <statement id="2" text="Local crafts, traditional skills, use of natural products, creativity of individual crafts people is the mobilizing resource of rural areas in Recife." type="">
   </statement>
   <statement id="3" text="Small cities in Den Bosch has structures like Public-private collaboration, with involvement of civic groups." type="">
   </statement>
   <statement id="4" text="table contains 8 context." type="">
   </statement>
   <statement id="5" text="The table contains 2 types of phase." type="">
   </statement>
   <statement id="6" text="Local crafts, traditional skills, use of natural products, creativity of individual crafts people is the mobilizing resource of rural areas in thailand." type="">
   </statement>
   <statement id="7" text="Large cities in Recife has structures like Public-private collaboration, with involvement of civic groups." type="">
   </statement>
   <statement id="8" text="The table contains 4 contexts." type="">
   </statement>
   <statement id="9" text="Conurbations in Nordrhein-Westfalen selects to Project team with input from individual makers." type="">
   </statement>
   <statement id="10" text="These are presented successively in terms of the preparation of creative development actions (inspiration, selection, structure) and the implementation phase (mobilizing resources, giving meanings and using creativity to links thing together)." type="">
   </statement>
  </statements>
 </table>
</document>