<Table 5>
 <caption text="

   Group Comparisons for ROCS Scales.
  
">
 </caption>
 <row row="0">
  <cell col="0" row="0" text="Scale">
  </cell>
  <cell col="1" row="0" text="OCD (
     
      n
     
     = 99)">
  </cell>
  <cell col="2" row="0" text="MDD (
     
      n
     
     = 74)">
  </cell>
  <cell col="3" row="0" text="HC (
     
      n
     
     = 35)">
  </cell>
 </row>
 <row row="1">
  <cell col="1" row="1" text="M (SD)">
  </cell>
  <cell col="2" row="1" text="M (SD)">
  </cell>
  <cell col="3" row="1" text="M (SD)">
  </cell>
 </row>
 <row row="2">
  <cell col="0" row="2" text="1. Total mental neutralizing">
  </cell>
  <cell col="1" row="2" text="1.79
     
      a
     
     (0.76)">
  </cell>
  <cell col="2" row="2" text="1.58
     
      b
     
     (0.66)">
  </cell>
  <cell col="3" row="2" text="0.92
     
      c
     
     (0.61)">
  </cell>
 </row>
 <row row="3">
  <cell col="0" row="3" text="2. Arguing with self">
  </cell>
  <cell col="1" row="3" text="1.98
     
      a
     
     (1.06)">
  </cell>
  <cell col="2" row="3" text="1.62
     
      b
     
     (0.87)">
  </cell>
  <cell col="3" row="3" text="1.13
     
      c
     
     (0.78)">
  </cell>
 </row>
 <row row="4">
  <cell col="0" row="4" text="3. Reconstruction and rituals">
  </cell>
  <cell col="1" row="4" text="1.74
     
      a
     
     (1.04)">
  </cell>
  <cell col="2" row="4" text="1.36
     
      b
     
     (0.80)">
  </cell>
  <cell col="3" row="4" text="0.51
     
      c
     
     (0.51)">
  </cell>
 </row>
 <row row="5">
  <cell col="0" row="5" text="4. Effort against thought">
  </cell>
  <cell col="1" row="5" text="1.72
     
      ab
     
     (0.95)">
  </cell>
  <cell col="2" row="5" text="1.76
     
      a
     
     (0.76)">
  </cell>
  <cell col="3" row="5" text="1.18
     
      b
     
     (0.81)">
  </cell>
 </row>
 <row row="6">
  <cell col="0" row="6" text="5. OCD symptom rumination">
  </cell>
  <cell col="1" row="6" text="2.26
     
      a
     
     (0.83)">
  </cell>
  <cell col="2" row="6" text="1.99
     
      a
     
     (0.96)">
  </cell>
  <cell col="3" row="6" text="1.87
     
      b
     
     (1.05)">
  </cell>
 </row>
 <row row="7">
  <cell col="0" row="7" text="6. Acceptance">
  </cell>
  <cell col="1" row="7" text="1.00
     
      a
     
     (0.87)">
  </cell>
  <cell col="2" row="7" text="1.45
     
      b
     
     (0.78)">
  </cell>
  <cell col="3" row="7" text="1.83
     
      c
     
     (1.00)">
  </cell>
 </row>
 <statements>
  <statement id="0" text="There are 6 different types of scale in the given table." type="entailed">
  </statement>
 </statements>
</Table 5>